femora/__init__.py
femora/constants.py
femora/components/MeshMaker.py
femora/components/__init__.py
femora/components/Actions/action.py
femora/components/Analysis/algorithms.py
femora/components/Analysis/algorithmsGUI.py
femora/components/Analysis/analysis.py
femora/components/Analysis/analysisGUI.py
femora/components/Analysis/base.py
femora/components/Analysis/constraint_handlers.py
femora/components/Analysis/constraint_handlersGUI.py
femora/components/Analysis/convergenceTests.py
femora/components/Analysis/convergenceTestsGUI.py
femora/components/Analysis/integrators.py
femora/components/Analysis/integratorsGUI.py
femora/components/Analysis/numberers.py
femora/components/Analysis/numberersGUI.py
femora/components/Analysis/systems.py
femora/components/Analysis/systemsGUI.py
femora/components/Assemble/Assembler.py
femora/components/Assemble/AssemblerGUI.py
femora/components/Constraint/constraint.py
femora/components/Constraint/mpConstraint.py
femora/components/Constraint/mpConstraintGUI.py
femora/components/Constraint/spConstraint.py
femora/components/Constraint/spConstraintGUI.py
femora/components/DRM/DRM.py
femora/components/DRM/__init__.py
femora/components/DRM/combinedDRMGUI.py
femora/components/DRM/drmAbsorbingGUI.py
femora/components/DRM/drmPatternGUI.py
femora/components/DRM/drmProcessGUI.py
femora/components/Damping/dampingBase.py
femora/components/Damping/dampingGUI.py
femora/components/Element/elementBase.py
femora/components/Element/elementGUI.py
femora/components/Element/element_class_manager.py
femora/components/Element/elementsOpenSees.py
femora/components/Element/elements_beam_gui.py
femora/components/Element/elements_opensees_beam.py
femora/components/Material/materialBase.py
femora/components/Material/materialGUI.py
femora/components/Material/materialsOpenSees.py
femora/components/Material/nd_uniaxial_manager.py
femora/components/Mesh/meshPartBase.py
femora/components/Mesh/meshPartGUI.py
femora/components/Mesh/meshPartInstance.py
femora-0.1.0.6.dist-info/METADATA
femora-0.1.0.6.dist-info/WHEEL
femora-0.1.0.6.dist-info/entry_points.txt
femora-0.1.0.6.dist-info/top_level.txt
femora-0.1.0.6.dist-info/RECORD
