Metadata-Version: 2.4
Name: femora
Version: 0.1.0.6
Summary: Fast Efficient Meshing for OpenSees-based Resilience Analysis
Author-email: Amin Pakzad <amnp95@uw.edu>, Pedro Arduino <parduino@uw.edu>
License: MIT
Project-URL: Homepage, https://github.com/amnp95/Femora
Project-URL: Documentation, https://amnp95.github.io/Femora
Project-URL: Repository, https://github.com/amnp95/Femora
Classifier: Programming Language :: Python :: 3
Classifier: License :: OSI Approved :: MIT License
Classifier: Operating System :: OS Independent
Requires-Python: >=3.9
Requires-Dist: h5py>=3.13.0
Requires-Dist: pykdtree>=1.4.1
Requires-Dist: pyvista>=0.45.0
Requires-Dist: tapipy>=1.8.2
Requires-Dist: vtk>=9.5.0
Requires-Dist: tqdm
Requires-Dist: scipy
Requires-Dist: meshlib
Requires-Dist: trame
Requires-Dist: trame-vtk
Requires-Dist: trame-vuetify
Provides-Extra: jupyter
Requires-Dist: pyvista[all]; extra == "jupyter"
Provides-Extra: gui
Requires-Dist: pyvistaqt>=0.11.2; extra == "gui"
Requires-Dist: PySide6>=6.9.0; extra == "gui"
Requires-Dist: QtPy>=2.4.3; extra == "gui"
Requires-Dist: qtconsole>=5.6.1; extra == "gui"
Requires-Dist: ipykernel>=6.29.5; extra == "gui"
Requires-Dist: jsonschema>=4.18.0; extra == "gui"
Requires-Dist: nbformat<5.4.0,>=5.3.0; extra == "gui"
Requires-Dist: frozenlist<1.4.0,>=1.3.0; extra == "gui"
Requires-Dist: jinja2<3.1.0,>=3.0.3; extra == "gui"
Provides-Extra: all
Requires-Dist: h5py>=3.13.0; extra == "all"
Requires-Dist: pykdtree>=1.4.1; extra == "all"
Requires-Dist: pyvista>=0.45.0; extra == "all"
Requires-Dist: pyvistaqt>=0.11.2; extra == "all"
Requires-Dist: PySide6>=6.9.0; extra == "all"
Requires-Dist: QtPy>=2.4.3; extra == "all"
Requires-Dist: qtconsole>=5.6.1; extra == "all"
Requires-Dist: ipykernel>=6.29.5; extra == "all"
Requires-Dist: tapipy>=1.8.2; extra == "all"
Requires-Dist: tqdm>=4.67.1; extra == "all"
Requires-Dist: scipy; extra == "all"
Requires-Dist: meshlib; extra == "all"
Requires-Dist: jsonschema<4.18.0,>=4.17.3; extra == "all"
Requires-Dist: nbformat<5.4.0,>=5.3.0; extra == "all"
Requires-Dist: frozenlist<1.4.0,>=1.3.0; extra == "all"
Requires-Dist: jinja2<3.1.0,>=3.0.3; extra == "all"
Provides-Extra: simcenter
Requires-Dist: h5py>=3.13.0; extra == "simcenter"
Requires-Dist: pykdtree>=1.4.1; extra == "simcenter"
Requires-Dist: pyvista>=0.45.0; extra == "simcenter"
Requires-Dist: tapipy>=1.8.2; extra == "simcenter"
Requires-Dist: vtk>=9.5.0; extra == "simcenter"
Requires-Dist: tqdm; extra == "simcenter"
Requires-Dist: scipy; extra == "simcenter"
Requires-Dist: meshlib; extra == "simcenter"
Requires-Dist: trame; extra == "simcenter"
Requires-Dist: trame-vtk; extra == "simcenter"
Requires-Dist: trame-vuetify; extra == "simcenter"
